trepan-0.6.4-py2.7-nspkg.pth
trepan-0.6.4.data/data/trepan/processor/command/help/examples.rst
trepan-0.6.4.data/data/trepan/processor/command/help/suffixes.rst
trepan-0.6.4.data/data/trepan/processor/command/help/location.rst
trepan-0.6.4.data/data/trepan/processor/command/help/command.rst
trepan-0.6.4.data/data/trepan/processor/command/help/filename.rst
trepan/VERSION.py
trepan/client.py
trepan/exception.py
trepan/api.py
trepan/vprocessor.py
trepan/options.py
trepan/interface.py
trepan/clifns.py
trepan/cli.py
trepan/post_mortem.py
trepan/bwcli.py
trepan/debugger.py
trepan/misc.py
trepan/lib/format.py
trepan/lib/complete.py
trepan/lib/__init__.py
trepan/lib/disassemble.py
trepan/lib/sighandler.py
trepan/lib/pp.py
trepan/lib/file.py
trepan/lib/eval.py
trepan/lib/thred.py
trepan/lib/display.py
trepan/lib/core.py
trepan/lib/breakpoint.py
trepan/lib/default.py
trepan/lib/bytecode.py
trepan/lib/printing.py
trepan/lib/stack.py
trepan/bwprocessor/__init__.py
trepan/bwprocessor/main.py
trepan/bwprocessor/location.py
trepan/bwprocessor/msg.py
trepan/processor/complete.py
trepan/processor/cmdproc.py
trepan/processor/trace.py
trepan/processor/cmdbreak.py
trepan/processor/cmdfns.py
trepan/processor/frame.py
trepan/processor/subcmd.py
trepan/processor/command/tbreak.py
trepan/processor/command/examine.py
trepan/processor/command/cd.py
trepan/processor/command/whatis.py
trepan/processor/command/debug.py
trepan/processor/command/skip.py
trepan/processor/command/alias.py
trepan/processor/command/list.py
trepan/processor/command/set.py
trepan/processor/command/__init__.py
trepan/processor/command/backtrace.py
trepan/processor/command/info.py
trepan/processor/command/ipython.py
trepan/processor/command/disassemble.py
trepan/processor/command/clear.py
trepan/processor/command/quit.py
trepan/processor/command/handle.py
trepan/processor/command/macro.py
trepan/processor/command/restart.py
trepan/processor/command/run.py
trepan-0.6.4.dist-info/METADATA
trepan-0.6.4.dist-info/WHEEL
trepan-0.6.4.dist-info/entry_points.txt
trepan-0.6.4.dist-info/RECORD
trepan-0.6.4.dist-info/top_level.txt
trepan-0.6.4.dist-info/DESCRIPTION.rst
trepan-0.6.4.dist-info/namespace_packages.txt
trepan-0.6.4.dist-info/metadata.json
