Metadata-Version: 2.0
Name: trepan
Version: 0.6.4
Summary: GDB-like Python Debugger in the Trepan family
Home-page: http://github.com/rocky/python2-trepan/
Author: Rocky Bernstein
Author-email: rocky@gnu.org
License: GPL
Platform: UNKNOWN
Classifier: Development Status :: 5 - Production/Stable
Classifier: Environment :: Console
Classifier: Intended Audience :: Developers
Classifier: License :: OSI Approved :: GNU General Public License (GPL)
Classifier: Operating System :: OS Independent
Classifier: Programming Language :: Python
Classifier: Topic :: Software Development :: Debuggers
Classifier: Topic :: Software Development :: Libraries :: Python Modules
Classifier: Programming Language :: Python :: 2.6
Classifier: Programming Language :: Python :: 2.7
Requires-Dist: columnize (>=0.3.8)
Requires-Dist: pyficache (>=0.3.0)
Requires-Dist: pygments (>=2.0.2)
Requires-Dist: uncompyle6 (>=2.1.2)
Requires-Dist: tracer (>=0.3.2)
